setup.py
F/EXT.py
F/__init__.py
F/CLASS/Callback.py
F/CLASS/Function.py
F/CLASS/Listener.py
F/CLASS/Promise.py
F/CLASS/Queue.py
F/CLASS/Routines.py
F/CLASS/Thread.py
F/CLASS/__init__.py
F/CONVERT/__init__.py
F/DATE/__init__.py
F/DICT/__init__.py
F/LIST/__init__.py
F/LOG/__init__.py
F/MATH/__init__.py
F/OS/__init__.py
FCoRE.egg-info/PKG-INFO
FCoRE.egg-info/SOURCES.txt
FCoRE.egg-info/dependency_links.txt
FCoRE.egg-info/requires.txt
FCoRE.egg-info/top_level.txt